uw_it/__init__.py
uw_it/flask_util/__init__.py
uw_it/flask_util/flask_gunicorn_log_config.yml
uw_it/flask_util/logger.py
uw_it_flask_gunicorn_json_logger-0.1.6.dist-info/LICENSE
uw_it_flask_gunicorn_json_logger-0.1.6.dist-info/WHEEL
uw_it_flask_gunicorn_json_logger-0.1.6.dist-info/METADATA
uw_it_flask_gunicorn_json_logger-0.1.6.dist-info/RECORD
