Metadata-Version: 2.1
Name: uw-it-flask-gunicorn-json-logger
Version: 0.1.6
Summary: 
Author: Tom Thorogood
Author-email: tom@tomthorogood.com
Requires-Python: >=3.7,<4
Classifier: Programming Language :: Python :: 3
Classifier: Programming Language :: Python :: 3.10
Classifier: Programming Language :: Python :: 3.7
Classifier: Programming Language :: Python :: 3.8
Classifier: Programming Language :: Python :: 3.9
Requires-Dist: Flask (>=2,<3)
Requires-Dist: PyYAML (>=6.0,<7.0)
